Workbook

Sheet Breakdown
A1: 9145 Ellis Road | D1: Call ID:
A2: Melbourne, FL 32904 | D2: Currency: | E2: USD
A3: www.ussiglobal.com | D3: Invoice Date: | E3: 36526
D4: Completed Date: | E4: 36526
D5: Customer:
D6: Terms: | E6: Net Amt Due in 45
A8: =CONCATENATE("PROFORMA INVOICE: ",TEXT(E4,"MMMM YYYY"))
A10: Workshop | B10: Units of Measure | C10: Unit Price | D10: Quantity | E10: Total Amount
A11: Standard ‘Basic’ Panel Triage & Repair Small (65”-75”) | B11: Each | C11: 110 | D11: =COUNTIFS('Depot Repair'!C:C,"BASIC",'Depot Repair'!D:D,"Small") | E11: =D11*C11
A12: Standard ‘Basic’ Panel Triage & Repair Large (86”) | B12: Each | C12: 135 | D12: =COUNTIFS('Depot Repair'!C:C,"BASIC",'Depot Repair'!D:D,"LARGE") | E12: =D12*C12
A13: Advanced ‘Heavy’ Panel Triage & Repairs Small (65”-75”) | B13: Each | C13: 220 | D13: =COUNTIFS('Depot Repair'!C:C,"Heavy",'Depot Repair'!D:D,"Small") | E13: =D13*C13
A14: Advanced ‘Heavy’ Panel Triage & Repairs Large (86”) | B14: Each | C14: 268 | D14: =COUNTIFS('Depot Repair'!C:C,"Heavy",'Depot Repair'!D:D,"Large") | E14: =D14*C14
A16: Standard ‘Basic’ Panel Triage Small (65”-75”) | B16: Each | C16: 86 | D16: =COUNTIFS('Triage Units'!D:D,"BasicSmall-Triage") | E16: =D16*C16
A17: Standard ‘Basic’ Panel Triage Large (86”) | B17: Each | C17: 101 | D17: =COUNTIFS('Triage Units'!D:D,"BasicLarge-Triage") | E17: =D17*C17
A18: Advanced ‘Heavy’ Panel Triage Small (65”-75”) | B18: Each | C18: 152 | D18: =COUNTIFS('Triage Units'!D:D,"HeavySmall-Triage") | E18: =D18*C18
A19: Advanced ‘Heavy’ Panel Triage Large (86”) | B19: Each | C19: 181 | D19: =COUNTIFS('Triage Units'!D:D,"HeavyLarge-Triage") | E19: =D19*C19
A21: Standard ‘Basic’ Panel Repair Small (65”-75”) | B21: Each | C21: 64 | D21: =COUNTIFS('Depot Repair'!C:C,"BasicSmall - Previously Triaged") | E21: =D21*C21
A22: Standard ‘Basic’ Panel Repair Large (86”) | B22: Each | C22: 74 | D22: =COUNTIFS('Depot Repair'!C:C,"BasicLarge - Previously Triaged") | E22: =D22*C22
A23: Advanced ‘Heavy’ Panel Repair Small (65”-75”) | B23: Each | C23: 108 | D23: =COUNTIFS('Depot Repair'!C:C,"HeavySmall - Previously Triaged") | E23: =D23*C23
A24: Advanced ‘Heavy’ Panel Repair Large (86”) | B24: Each | C24: 127 | D24: =COUNTIFS('Depot Repair'!C:C,"HeavyLarge - Previously Triaged") | E24: =D24*C24
A26: Reboxing Fee | B26: Each | C26: 50 | D26: 0 | E26: =D26*C26
A28: Immediate Scrap | B28: Each | C28: 19 | D28: =COUNTIFS('Depot Repair'!C:C,"Immediate Scrap") | E28: =D28*C28
A29: Salvage of Hardware and Scrap | B29: Each | C29: 28 | D29: =COUNTIFS('Depot Repair'!C:C,"Salvage of Hardware and Scrap") | E29: =D29*C29
A31: Special Warehouse Projects | B31: Hourly | C31: 75 | D31: 0 | E31: =D31*C31
A33: Parts Testing & Configuration | B33: Units of Measure | C33: Unit Price | D33: Quantity | E33: Total Amount
A34: PSU - Testing | B34: Each | C34: 7 | D34: =SUMIFS(TblPartTesting[Quantity],TblPartTesting[Type],"PSU") | E34: =D34*C34
A35: Mainboard Configure for Dispatch - Testing | B35: Each | C35: 52 | D35: =SUMIFS(TblPartTesting[Quantity],TblPartTesting[Type],"Mainboard Configure for Dispatch") | E35: =D35*C35
A36: Mainboard - Testing | B36: Each | C36: 37 | D36: =SUMIFS(TblPartTesting[Quantity],TblPartTesting[Type],"Mainboard") | E36: =D36*C36
A37: AC-PCA - Testing | B37: Each | C37: 4 | D37: =SUMIFS(TblPartTesting[Quantity],TblPartTesting[Type],"AC-PCA") | E37: =D37*C37
A38: Keypad - Testing | B38: Each | C38: 4 | D38: =SUMIFS(TblPartTesting[Quantity],TblPartTesting[Type],"Keypad") | E38: =D38*C38
A39: Maintouch - Testing | B39: Each | C39: 37 | D39: =SUMIFS(TblPartTesting[Quantity],TblPartTesting[Type],"Maintouch") | E39: =D39*C39
A40: Ext-Input - Testing | B40: Each | C40: 7 | D40: =SUMIFS(TblPartTesting[Quantity],TblPartTesting[Type],"EXT-INPUT") | E40: =D40*C40
A41: OPS-PCA - Testing | B41: Each | C41: 4 | D41: =SUMIFS(TblPartTesting[Quantity],TblPartTesting[Type],"OPS-PCA") | E41: =D41*C41
A42: USB - Testing | B42: Each | C42: 4 | D42: =SUMIFS(TblPartTesting[Quantity],TblPartTesting[Type],"USB") | E42: =D42*C42
A43: Speaker Testing | B43: Each | C43: 4 | D43: =SUMIFS(TblPartTesting[Quantity],TblPartTesting[Type],"SPEAKER") | E43: =D43*C43
D45: Subtotal | E45: =SUM(E11:E43)
D46: Tax | E46: =E45*7%
D47: Total | E47: =SUM(E45:E46)

Sheet Depot Repair
A1: Model | B1: Serial | C1: Type | D1: Size | E1: Repair Cost | F1: Parts Summary

Sheet Triage Units
A1: Model | B1: Serial | C1: Triage | D1: Derived Type | E1: Size | F1: Cost

Sheet Part Testing & Programming
A1: MSO | B1: Request Date | C1: Outbound Tracking | D1: Part # | E1: Type | F1: Serial | G1: Quantity | H1: Individual Part Fee | I1: Total Programming Fee | J1: Part Pick Fee

Sheet Excluded Serials
A1: Model | B1: Serial | C1: Source Tab | D1: Category | E1: Result | F1: Original Date | G1: Reason
